agentslack/README.md
agentslack/Slack.py
agentslack/__init__.py
agentslack/api.py
agentslack/client.py
agentslack/registry.py
agentslack/run.py
agentslack/types.py
agentslack/validate.py
agentslack-1.0.4.dist-info/METADATA
agentslack-1.0.4.dist-info/WHEEL
agentslack-1.0.4.dist-info/licenses/LICENSE
agentslack-1.0.4.dist-info/RECORD
