Metadata-Version: 2.4
Name: agentslack
Version: 1.0.4
Summary: A Python SDK for building multi-agent worlds that communicate through Slack.
Project-URL: Homepage, https://github.com/princeton-pli/agentslack
Project-URL: Documentation, https://github.com/princeton-pli/agentslack/blob/main/src/agentslack/README.md
Author-email: Veniamin Veselovsky <veniamin@princeton.edu>, Benedikt Stroebl <stroebl@princeton.edu>
License-Expression: MIT
License-File: LICENSE
Classifier: Intended Audience :: Developers
Classifier: License :: OSI Approved :: MIT License
Classifier: Operating System :: OS Independent
Classifier: Programming Language :: Python :: 3
Classifier: Programming Language :: Python :: 3.11
Classifier: Topic :: Communications :: Chat
Requires-Python: >=3.11
Requires-Dist: fastapi>=0.115.0
Requires-Dist: pydantic>=2.0.0
Requires-Dist: python-dotenv>=1.0.0
Requires-Dist: requests>=2.31.0
Requires-Dist: slack-sdk>=3.34.0
Requires-Dist: tqdm>=4.67.1
Requires-Dist: uvicorn>=0.34.0
Provides-Extra: demo
Requires-Dist: litellm>=1.59.0; extra == 'demo'
Requires-Dist: smolagents>=1.4.1; extra == 'demo'
